pifi/Adafruit_I2C.py
pifi/MusicTrack.py
pifi/LCDScreen.py
pifi/MusicController.py
pifi/WaitForMultipleEvents.py
pifi/SpectrumAnalyzer.py
pifi/__init__.py
pifi/Adafruit_CharLCDPlate.py
PiFi-1.0.0.dist-info/DESCRIPTION.rst
PiFi-1.0.0.dist-info/WHEEL
PiFi-1.0.0.dist-info/METADATA
PiFi-1.0.0.dist-info/entry_points.txt
PiFi-1.0.0.dist-info/RECORD
PiFi-1.0.0.dist-info/top_level.txt
PiFi-1.0.0.dist-info/metadata.json
