Metadata-Version: 2.0
Name: PiFi
Version: 1.0.0
Summary: Hi Fi music hub on Raspberry Pi
Home-page: https://bitbucket.org/bertrandboichon/pi.hifi
Author: Bertrand Boichon
Author-email: b.boichon@gmail.com
License: MIT
Keywords: music mpd hifi raspberry pi rpi
Platform: UNKNOWN
Classifier: Development Status :: 3 - Alpha
Classifier: Intended Audience :: Developers
Classifier: Topic :: Multimedia :: Sound/Audio :: Players
Classifier: License :: OSI Approved :: MIT License
Classifier: Programming Language :: Python :: 2
Classifier: Programming Language :: Python :: 2.6
Classifier: Programming Language :: Python :: 2.7
Classifier: Programming Language :: Python :: 3
Classifier: Programming Language :: Python :: 3.2
Classifier: Programming Language :: Python :: 3.3
Classifier: Programming Language :: Python :: 3.4
Requires-Dist: python-mpd2
Requires-Dist: evdev
Requires-Dist: RPi.GPIO
Requires-Dist: numpy
